annotateonline/__init__.py
annotateonline/__main__.py
annotateonline/image_upload/__init__.py
annotateonline/image_upload/start.py
annotateonline/pre_annotation_upload/__init__.py
annotateonline/pre_annotation_upload/coco_convert.py
annotateonline/pre_annotation_upload/pixel_convert.py
annotateonline/pre_annotation_upload/start.py
annotateonline/pre_annotation_upload/panopticapi/__init__.py
annotateonline/pre_annotation_upload/panopticapi/combine_semantic_and_instance_predictions.py
annotateonline/pre_annotation_upload/panopticapi/evaluation.py
annotateonline/pre_annotation_upload/panopticapi/utils.py
annotateonline-0.1.34.dist-info/LICENSE
annotateonline-0.1.34.dist-info/METADATA
annotateonline-0.1.34.dist-info/WHEEL
annotateonline-0.1.34.dist-info/entry_points.txt
annotateonline-0.1.34.dist-info/top_level.txt
annotateonline-0.1.34.dist-info/RECORD
