Metadata-Version: 2.1
Name: annotateonline
Version: 0.1.34
Summary: Annotate Online
Home-page: https://github.com/superannotateai/AO-python-cli
Author: Annotate Online
Author-email: UNKNOWN
License: MIT
Platform: UNKNOWN
Requires-Dist: boto3
Requires-Dist: pillow
Requires-Dist: cython
Requires-Dist: numpy
Requires-Dist: pycocotools
Requires-Dist: matplotlib
Requires-Dist: opencv-python
